usfm_references/__init__.py
usfm_references/books.py
usfm_references/reference.py
usfm_references-2.0.0.dist-info/LICENSE.md
usfm_references-2.0.0.dist-info/METADATA
usfm_references-2.0.0.dist-info/WHEEL
usfm_references-2.0.0.dist-info/top_level.txt
usfm_references-2.0.0.dist-info/RECORD
