Metadata-Version: 2.1
Name: usfm-references
Version: 2.0.0
Summary: Tools to work with USFM references
Home-page: https://github.com/bbelyeu/usfm-references
Author: Brad Belyeu
Author-email: bradleylamar@gmail.com
License: MIT
Download-URL: https://github.com/bbelyeu/usfm-references/archive/2.0.0.zip
Platform: any
Classifier: Intended Audience :: Developers
Classifier: License :: OSI Approved :: MIT License
Classifier: Operating System :: OS Independent
Classifier: Programming Language :: Python
Classifier: Programming Language :: Python :: 3
Classifier: Programming Language :: Python :: 3.9
Classifier: Programming Language :: Python :: 3.10
Classifier: Programming Language :: Python :: 3.11
Classifier: Programming Language :: Python :: 3.12
Classifier: Topic :: Software Development :: Libraries :: Python Modules
License-File: LICENSE.md
